{"74208011136":{"id":"2131110748","fullName":"\\N \\N \\N","firstName":"\\N","lastName":"\\N","middleName":"\\N","gender":"\\N","birthDate":"\\N","birthPlace":"\\N","passportData":"\\N \\N \\N \\N","inn":"4208011136","address":"f","phone":"74208011136","formattedPhone":"+7 (420) 801-11-36"},"74213009012":{"id":"647669405","fullName":"\\N \\N \\N","firstName":"\\N","lastName":"\\N","middleName":"\\N","gender":"\\N","birthDate":"\\N","birthPlace":"\\N","passportData":"\\N \\N \\N \\N","inn":"4213009012","address":"f","phone":"74213009012","formattedPhone":"+7 (421) 300-90-12"},"74241000371":{"id":"659717327","fullName":"\\N \\N \\N","firstName":"\\N","lastName":"\\N","middleName":"\\N","gender":"\\N","birthDate":"\\N","birthPlace":"\\N","passportData":"\\N \\N \\N \\N","inn":"4241000371","address":"f","phone":"74241000371","formattedPhone":"+7 (424) 100-03-71"},"74205003585":{"id":"661952101","fullName":"\\N \\N \\N","firstName":"\\N","lastName":"\\N","middleName":"\\N","gender":"\\N","birthDate":"\\N","birthPlace":"\\N","passportData":"\\N \\N \\N \\N","inn":"4205003585","address":"f","phone":"74205003585","formattedPhone":"+7 (420) 500-35-85"},"74207023795":{"id":"644093768","fullName":"\\N \\N \\N","firstName":"\\N","lastName":"\\N","middleName":"\\N","gender":"\\N","birthDate":"\\N","birthPlace":"\\N","passportData":"\\N \\N \\N \\N","inn":"4207023795","address":"f","phone":"74207023795","formattedPhone":"+7 (420) 702-37-95"},"74205258230":{"id":"1513021397","fullName":"\\N \\N \\N","firstName":"\\N","lastName":"\\N","middleName":"\\N","gender":"\\N","birthDate":"\\N","birthPlace":"\\N","passportData":"\\N \\N \\N \\N","inn":"4205258230","address":"f","phone":"74205258230","formattedPhone":"+7 (420) 525-82-30"},"74200000446":{"id":"644094042","fullName":"\\N \\N \\N","firstName":"\\N","lastName":"\\N","middleName":"\\N","gender":"\\N","birthDate":"\\N","birthPlace":"\\N","passportData":"\\N \\N \\N \\N","inn":"4200000446","address":"f","phone":"74200000446","formattedPhone":"+7 (420) 000-04-46"},"74223712778":{"id":"1356759577","fullName":"\\N \\N \\N","firstName":"\\N","lastName":"\\N","middleName":"\\N","gender":"\\N","birthDate":"\\N","birthPlace":"\\N","passportData":"\\N \\N \\N \\N","inn":"4223712778","address":"f","phone":"74223712778","formattedPhone":"+7 (422) 371-27-78"},"74202022188":{"id":"644094049","fullName":"\\N \\N \\N","firstName":"\\N","lastName":"\\N","middleName":"\\N","gender":"\\N","birthDate":"\\N","birthPlace":"\\N","passportData":"\\N \\N \\N \\N","inn":"4202022188","address":"f","phone":"74202022188","formattedPhone":"+7 (420) 202-21-88"},"74205233204":{"id":"2131125151","fullName":"\\N \\N \\N","firstName":"\\N","lastName":"\\N","middleName":"\\N","gender":"\\N","birthDate":"\\N","birthPlace":"\\N","passportData":"\\N \\N \\N \\N","inn":"4205233204","address":"f","phone":"74205233204","formattedPhone":"+7 (420) 523-32-04"},"74205058930":{"id":"659310759","fullName":"\\N \\N \\N","firstName":"\\N","lastName":"\\N","middleName":"\\N","gender":"\\N","birthDate":"\\N","birthPlace":"\\N","passportData":"\\N \\N \\N \\N","inn":"4205058930","address":"f","phone":"74205058930","formattedPhone":"+7 (420) 505-89-30"},"74240002697":{"id":"2185116633","fullName":"\\N \\N \\N","firstName":"\\N","lastName":"\\N","middleName":"\\N","gender":"\\N","birthDate":"\\N","birthPlace":"\\N","passportData":"\\N \\N \\N \\N","inn":"4240002697","address":"f","phone":"74240002697","formattedPhone":"+7 (424) 000-26-97"},"74205109750":{"id":"1222375000","fullName":"\\N \\N \\N","firstName":"\\N","lastName":"\\N","middleName":"\\N","gender":"\\N","birthDate":"\\N","birthPlace":"\\N","passportData":"\\N \\N \\N \\N","inn":"4205109750","address":"f","phone":"74205109750","formattedPhone":"+7 (420) 510-97-50"},"74205394378":{"id":"2216189119","fullName":"\\N \\N \\N","firstName":"\\N","lastName":"\\N","middleName":"\\N","gender":"\\N","birthDate":"\\N","birthPlace":"\\N","passportData":"\\N \\N \\N \\N","inn":"4205394378","address":"f","phone":"74205394378","formattedPhone":"+7 (420) 539-43-78"},"74240005497":{"id":"2147757601","fullName":"\\N \\N \\N","firstName":"\\N","lastName":"\\N","middleName":"\\N","gender":"\\N","birthDate":"\\N","birthPlace":"\\N","passportData":"\\N \\N \\N \\N","inn":"4240005497","address":"f","phone":"74240005497","formattedPhone":"+7 (424) 000-54-97"},"74200000319":{"id":"637636198","fullName":"\\N \\N \\N","firstName":"\\N","lastName":"\\N","middleName":"\\N","gender":"\\N","birthDate":"\\N","birthPlace":"\\N","passportData":"\\N \\N \\N \\N","inn":"4200000319","address":"f","phone":"74200000319","formattedPhone":"+7 (420) 000-03-19"},"74234000571":{"id":"647669538","fullName":"\\N \\N \\N","firstName":"\\N","lastName":"\\N","middleName":"\\N","gender":"\\N","birthDate":"\\N","birthPlace":"\\N","passportData":"\\N \\N \\N \\N","inn":"4234000571","address":"f","phone":"74234000571","formattedPhone":"+7 (423) 400-05-71"},"74205091920":{"id":"644094454","fullName":"\\N \\N \\N","firstName":"\\N","lastName":"\\N","middleName":"\\N","gender":"\\N","birthDate":"\\N","birthPlace":"\\N","passportData":"\\N \\N \\N \\N","inn":"4205091920","address":"f","phone":"74205091920","formattedPhone":"+7 (420) 509-19-20"},"74211022378":{"id":"644093897","fullName":"\\N \\N \\N","firstName":"\\N","lastName":"\\N","middleName":"\\N","gender":"\\N","birthDate":"\\N","birthPlace":"\\N","passportData":"\\N \\N \\N \\N","inn":"4211022378","address":"f","phone":"74211022378","formattedPhone":"+7 (421) 102-23-78"},"74205109101":{"id":"953595809","fullName":"\\N \\N \\N","firstName":"\\N","lastName":"\\N","middleName":"\\N","gender":"\\N","birthDate":"\\N","birthPlace":"\\N","passportData":"\\N \\N \\N \\N","inn":"4205109101","address":"f","phone":"74205109101","formattedPhone":"+7 (420) 510-91-01"},"74246003993":{"id":"647669507","fullName":"\\N \\N \\N","firstName":"\\N","lastName":"\\N","middleName":"\\N","gender":"\\N","birthDate":"\\N","birthPlace":"\\N","passportData":"\\N \\N \\N \\N","inn":"4246003993","address":"f","phone":"74246003993","formattedPhone":"+7 (424) 600-39-93"},"74205107224":{"id":"2147756833","fullName":"\\N \\N \\N","firstName":"\\N","lastName":"\\N","middleName":"\\N","gender":"\\N","birthDate":"\\N","birthPlace":"\\N","passportData":"\\N \\N \\N \\N","inn":"4205107224","address":"f","phone":"74205107224","formattedPhone":"+7 (420) 510-72-24"},"74230005963":{"id":"1159071797","fullName":"\\N \\N \\N","firstName":"\\N","lastName":"\\N","middleName":"\\N","gender":"\\N","birthDate":"\\N","birthPlace":"\\N","passportData":"\\N \\N \\N \\N","inn":"4230005963","address":"f","phone":"74230005963","formattedPhone":"+7 (423) 000-59-63"},"74230016838":{"id":"637634269","fullName":"\\N \\N \\N","firstName":"\\N","lastName":"\\N","middleName":"\\N","gender":"\\N","birthDate":"\\N","birthPlace":"\\N","passportData":"\\N \\N \\N \\N","inn":"4230016838","address":"f","phone":"74230016838","formattedPhone":"+7 (423) 001-68-38"},"74205197549":{"id":"2131113596","fullName":"\\N \\N \\N","firstName":"\\N","lastName":"\\N","middleName":"\\N","gender":"\\N","birthDate":"\\N","birthPlace":"\\N","passportData":"\\N \\N \\N \\N","inn":"4205197549","address":"f","phone":"74205197549","formattedPhone":"+7 (420) 519-75-49"},"74205077474":{"id":"1356753572","fullName":"\\N \\N \\N","firstName":"\\N","lastName":"\\N","middleName":"\\N","gender":"\\N","birthDate":"\\N","birthPlace":"\\N","passportData":"\\N \\N \\N \\N","inn":"4205077474","address":"f","phone":"74205077474","formattedPhone":"+7 (420) 507-74-74"},"74207004665":{"id":"661952784","fullName":"\\N \\N \\N","firstName":"\\N","lastName":"\\N","middleName":"\\N","gender":"\\N","birthDate":"\\N","birthPlace":"\\N","passportData":"\\N \\N \\N \\N","inn":"4207004665","address":"f","phone":"74207004665","formattedPhone":"+7 (420) 700-46-65"},"74230002634":{"id":"2147757927","fullName":"\\N \\N \\N","firstName":"\\N","lastName":"\\N","middleName":"\\N","gender":"\\N","birthDate":"\\N","birthPlace":"\\N","passportData":"\\N \\N \\N \\N","inn":"4230002634","address":"f","phone":"74230002634","formattedPhone":"+7 (423) 000-26-34"},"74217108455":{"id":"2147757522","fullName":"\\N \\N \\N","firstName":"\\N","lastName":"\\N","middleName":"\\N","gender":"\\N","birthDate":"\\N","birthPlace":"\\N","passportData":"\\N \\N \\N \\N","inn":"4217108455","address":"f","phone":"74217108455","formattedPhone":"+7 (421) 710-84-55"},"74213005280":{"id":"2185118300","fullName":"\\N \\N \\N","firstName":"\\N","lastName":"\\N","middleName":"\\N","gender":"\\N","birthDate":"\\N","birthPlace":"\\N","passportData":"\\N \\N \\N \\N","inn":"4213005280","address":"f","phone":"74213005280","formattedPhone":"+7 (421) 300-52-80"},"74216002921":{"id":"644093870","fullName":"\\N \\N \\N","firstName":"\\N","lastName":"\\N","middleName":"\\N","gender":"\\N","birthDate":"\\N","birthPlace":"\\N","passportData":"\\N \\N \\N \\N","inn":"4216002921","address":"f","phone":"74216002921","formattedPhone":"+7 (421) 600-29-21"},"74222010511":{"id":"2147758641","fullName":"\\N \\N \\N","firstName":"\\N","lastName":"\\N","middleName":"\\N","gender":"\\N","birthDate":"\\N","birthPlace":"\\N","passportData":"\\N \\N \\N \\N","inn":"4222010511","address":"f","phone":"74222010511","formattedPhone":"+7 (422) 201-05-11"},"74205173234":{"id":"661959292","fullName":"\\N \\N \\N","firstName":"\\N","lastName":"\\N","middleName":"\\N","gender":"\\N","birthDate":"\\N","birthPlace":"\\N","passportData":"\\N \\N \\N \\N","inn":"4205173234","address":"f","phone":"74205173234","formattedPhone":"+7 (420) 517-32-34"},"74253034022":{"id":"2131130829","fullName":"\\N \\N \\N","firstName":"\\N","lastName":"\\N","middleName":"\\N","gender":"\\N","birthDate":"\\N","birthPlace":"\\N","passportData":"\\N \\N \\N \\N","inn":"4253034022","address":"f","phone":"74253034022","formattedPhone":"+7 (425) 303-40-22"},"74203001913":{"id":"2159772008","fullName":"\\N \\N \\N","firstName":"\\N","lastName":"\\N","middleName":"\\N","gender":"\\N","birthDate":"\\N","birthPlace":"\\N","passportData":"\\N \\N \\N \\N","inn":"4203001913","address":"f","phone":"74203001913","formattedPhone":"+7 (420) 300-19-13"},"74214000608":{"id":"644094224","fullName":"\\N \\N \\N","firstName":"\\N","lastName":"\\N","middleName":"\\N","gender":"\\N","birthDate":"\\N","birthPlace":"\\N","passportData":"\\N \\N \\N \\N","inn":"4214000608","address":"f","phone":"74214000608","formattedPhone":"+7 (421) 400-06-08"},"74214000615":{"id":"644094211","fullName":"\\N \\N \\N","firstName":"\\N","lastName":"\\N","middleName":"\\N","gender":"\\N","birthDate":"\\N","birthPlace":"\\N","passportData":"\\N \\N \\N \\N","inn":"4214000615","address":"f","phone":"74214000615","formattedPhone":"+7 (421) 400-06-15"},"74200000083":{"id":"644093982","fullName":"\\N \\N \\N","firstName":"\\N","lastName":"\\N","middleName":"\\N","gender":"\\N","birthDate":"\\N","birthPlace":"\\N","passportData":"\\N \\N \\N \\N","inn":"4200000083","address":"f","phone":"74200000083","formattedPhone":"+7 (420) 000-00-83"},"74238024809":{"id":"2229647309","fullName":"\\N \\N \\N","firstName":"\\N","lastName":"\\N","middleName":"\\N","gender":"\\N","birthDate":"\\N","birthPlace":"\\N","passportData":"\\N \\N \\N \\N","inn":"4238024809","address":"f","phone":"74238024809","formattedPhone":"+7 (423) 802-48-09"},"74246004891":{"id":"2016080833","fullName":"\\N \\N \\N","firstName":"\\N","lastName":"\\N","middleName":"\\N","gender":"\\N","birthDate":"\\N","birthPlace":"\\N","passportData":"\\N \\N \\N \\N","inn":"4246004891","address":"f","phone":"74246004891","formattedPhone":"+7 (424) 600-48-91"},"74246003496":{"id":"2147765068","fullName":"\\N \\N \\N","firstName":"\\N","lastName":"\\N","middleName":"\\N","gender":"\\N","birthDate":"\\N","birthPlace":"\\N","passportData":"\\N \\N \\N \\N","inn":"4246003496","address":"f","phone":"74246003496","formattedPhone":"+7 (424) 600-34-96"},"74217092325":{"id":"2010083497","fullName":"\\N \\N \\N","firstName":"\\N","lastName":"\\N","middleName":"\\N","gender":"\\N","birthDate":"\\N","birthPlace":"\\N","passportData":"\\N \\N \\N \\N","inn":"4217092325","address":"f","phone":"74217092325","formattedPhone":"+7 (421) 709-23-25"},"74216004076":{"id":"2147765069","fullName":"\\N \\N \\N","firstName":"\\N","lastName":"\\N","middleName":"\\N","gender":"\\N","birthDate":"\\N","birthPlace":"\\N","passportData":"\\N \\N \\N \\N","inn":"4216004076","address":"f","phone":"74216004076","formattedPhone":"+7 (421) 600-40-76"},"74205046395":{"id":"661958870","fullName":"\\N \\N \\N","firstName":"\\N","lastName":"\\N","middleName":"\\N","gender":"\\N","birthDate":"\\N","birthPlace":"\\N","passportData":"\\N \\N \\N \\N","inn":"4205046395","address":"f","phone":"74205046395","formattedPhone":"+7 (420) 504-63-95"},"74205225450":{"id":"661958865","fullName":"\\N \\N \\N","firstName":"\\N","lastName":"\\N","middleName":"\\N","gender":"\\N","birthDate":"\\N","birthPlace":"\\N","passportData":"\\N \\N \\N \\N","inn":"4205225450","address":"f","phone":"74205225450","formattedPhone":"+7 (420) 522-54-50"},"74214038915":{"id":"2147758540","fullName":"\\N \\N \\N","firstName":"\\N","lastName":"\\N","middleName":"\\N","gender":"\\N","birthDate":"\\N","birthPlace":"\\N","passportData":"\\N \\N \\N \\N","inn":"4214038915","address":"f","phone":"74214038915","formattedPhone":"+7 (421) 403-89-15"},"74248000677":{"id":"659717350","fullName":"\\N \\N \\N","firstName":"\\N","lastName":"\\N","middleName":"\\N","gender":"\\N","birthDate":"\\N","birthPlace":"\\N","passportData":"\\N \\N \\N \\N","inn":"4248000677","address":"f","phone":"74248000677","formattedPhone":"+7 (424) 800-06-77"},"74205085115":{"id":"661959680","fullName":"\\N \\N \\N","firstName":"\\N","lastName":"\\N","middleName":"\\N","gender":"\\N","birthDate":"\\N","birthPlace":"\\N","passportData":"\\N \\N \\N \\N","inn":"4205085115","address":"f","phone":"74205085115","formattedPhone":"+7 (420) 508-51-15"},"74223020921":{"id":"1513030712","fullName":"\\N \\N \\N","firstName":"\\N","lastName":"\\N","middleName":"\\N","gender":"\\N","birthDate":"\\N","birthPlace":"\\N","passportData":"\\N \\N \\N \\N","inn":"4223020921","address":"f","phone":"74223020921","formattedPhone":"+7 (422) 302-09-21"},"74223044136":{"id":"644094668","fullName":"\\N \\N \\N","firstName":"\\N","lastName":"\\N","middleName":"\\N","gender":"\\N","birthDate":"\\N","birthPlace":"\\N","passportData":"\\N \\N \\N \\N","inn":"4223044136","address":"f","phone":"74223044136","formattedPhone":"+7 (422) 304-41-36"},"74202030580":{"id":"644094662","fullName":"\\N \\N \\N","firstName":"\\N","lastName":"\\N","middleName":"\\N","gender":"\\N","birthDate":"\\N","birthPlace":"\\N","passportData":"\\N \\N \\N \\N","inn":"4202030580","address":"f","phone":"74202030580","formattedPhone":"+7 (420) 203-05-80"},"74205003440":{"id":"644094570","fullName":"\\N \\N \\N","firstName":"\\N","lastName":"\\N","middleName":"\\N","gender":"\\N","birthDate":"\\N","birthPlace":"\\N","passportData":"\\N \\N \\N \\N","inn":"4205003440","address":"f","phone":"74205003440","formattedPhone":"+7 (420) 500-34-40"},"74205153492":{"id":"2148805450","fullName":"\\N \\N \\N","firstName":"\\N","lastName":"\\N","middleName":"\\N","gender":"\\N","birthDate":"\\N","birthPlace":"\\N","passportData":"\\N \\N \\N \\N","inn":"4205153492","address":"f","phone":"74205153492","formattedPhone":"+7 (420) 515-34-92"},"74217132183":{"id":"2131137095","fullName":"\\N \\N \\N","firstName":"\\N","lastName":"\\N","middleName":"\\N","gender":"\\N","birthDate":"\\N","birthPlace":"\\N","passportData":"\\N \\N \\N \\N","inn":"4217132183","address":"f","phone":"74217132183","formattedPhone":"+7 (421) 713-21-83"},"74213009679":{"id":"2195848792","fullName":"\\N \\N \\N","firstName":"\\N","lastName":"\\N","middleName":"\\N","gender":"\\N","birthDate":"\\N","birthPlace":"\\N","passportData":"\\N \\N \\N \\N","inn":"4213009679","address":"f","phone":"74213009679","formattedPhone":"+7 (421) 300-96-79"},"74228009488":{"id":"2147759127","fullName":"\\N \\N \\N","firstName":"\\N","lastName":"\\N","middleName":"\\N","gender":"\\N","birthDate":"\\N","birthPlace":"\\N","passportData":"\\N \\N \\N \\N","inn":"4228009488","address":"f","phone":"74228009488","formattedPhone":"+7 (422) 800-94-88"},"74205327727":{"id":"1513030290","fullName":"\\N \\N \\N","firstName":"\\N","lastName":"\\N","middleName":"\\N","gender":"\\N","birthDate":"\\N","birthPlace":"\\N","passportData":"\\N \\N \\N \\N","inn":"4205327727","address":"f","phone":"74205327727","formattedPhone":"+7 (420) 532-77-27"},"74240005761":{"id":"644094068","fullName":"\\N \\N \\N","firstName":"\\N","lastName":"\\N","middleName":"\\N","gender":"\\N","birthDate":"\\N","birthPlace":"\\N","passportData":"\\N \\N \\N \\N","inn":"4240005761","address":"f","phone":"74240005761","formattedPhone":"+7 (424) 000-57-61"},"74207009455":{"id":"659310792","fullName":"\\N \\N \\N","firstName":"\\N","lastName":"\\N","middleName":"\\N","gender":"\\N","birthDate":"\\N","birthPlace":"\\N","passportData":"\\N \\N \\N \\N","inn":"4207009455","address":"f","phone":"74207009455","formattedPhone":"+7 (420) 700-94-55"},"74205052085":{"id":"659310766","fullName":"\\N \\N \\N","firstName":"\\N","lastName":"\\N","middleName":"\\N","gender":"\\N","birthDate":"\\N","birthPlace":"\\N","passportData":"\\N \\N \\N \\N","inn":"4205052085","address":"f","phone":"74205052085","formattedPhone":"+7 (420) 505-20-85"},"74205059250":{"id":"637635951","fullName":"\\N \\N \\N","firstName":"\\N","lastName":"\\N","middleName":"\\N","gender":"\\N","birthDate":"\\N","birthPlace":"\\N","passportData":"\\N \\N \\N \\N","inn":"4205059250","address":"f","phone":"74205059250","formattedPhone":"+7 (420) 505-92-50"},"74244001408":{"id":"2195848265","fullName":"\\N \\N \\N","firstName":"\\N","lastName":"\\N","middleName":"\\N","gender":"\\N","birthDate":"\\N","birthPlace":"\\N","passportData":"\\N \\N \\N \\N","inn":"4244001408","address":"f","phone":"74244001408","formattedPhone":"+7 (424) 400-14-08"},"74205211803":{"id":"2348339995","fullName":"\\N \\N \\N","firstName":"\\N","lastName":"\\N","middleName":"\\N","gender":"\\N","birthDate":"\\N","birthPlace":"\\N","passportData":"\\N \\N \\N \\N","inn":"4205211803","address":"f","phone":"74205211803","formattedPhone":"+7 (420) 521-18-03"},"74212015729":{"id":"2010086398","fullName":"\\N \\N \\N","firstName":"\\N","lastName":"\\N","middleName":"\\N","gender":"\\N","birthDate":"\\N","birthPlace":"\\N","passportData":"\\N \\N \\N \\N","inn":"4212015729","address":"f","phone":"74212015729","formattedPhone":"+7 (421) 201-57-29"},"74205096445":{"id":"2131146111","fullName":"\\N \\N \\N","firstName":"\\N","lastName":"\\N","middleName":"\\N","gender":"\\N","birthDate":"\\N","birthPlace":"\\N","passportData":"\\N \\N \\N \\N","inn":"4205096445","address":"f","phone":"74205096445","formattedPhone":"+7 (420) 509-64-45"},"74213010770":{"id":"2147760872","fullName":"\\N \\N \\N","firstName":"\\N","lastName":"\\N","middleName":"\\N","gender":"\\N","birthDate":"\\N","birthPlace":"\\N","passportData":"\\N \\N \\N \\N","inn":"4213010770","address":"f","phone":"74213010770","formattedPhone":"+7 (421) 301-07-70"},"74213002779":{"id":"2147760893","fullName":"\\N \\N \\N","firstName":"\\N","lastName":"\\N","middleName":"\\N","gender":"\\N","birthDate":"\\N","birthPlace":"\\N","passportData":"\\N \\N \\N \\N","inn":"4213002779","address":"f","phone":"74213002779","formattedPhone":"+7 (421) 300-27-79"},"74247002463":{"id":"2147760453","fullName":"\\N \\N \\N","firstName":"\\N","lastName":"\\N","middleName":"\\N","gender":"\\N","birthDate":"\\N","birthPlace":"\\N","passportData":"\\N \\N \\N \\N","inn":"4247002463","address":"f","phone":"74247002463","formattedPhone":"+7 (424) 700-24-63"},"74215003182":{"id":"2147760608","fullName":"\\N \\N \\N","firstName":"\\N","lastName":"\\N","middleName":"\\N","gender":"\\N","birthDate":"\\N","birthPlace":"\\N","passportData":"\\N \\N \\N \\N","inn":"4215003182","address":"f","phone":"74215003182","formattedPhone":"+7 (421) 500-31-82"},"74201002421":{"id":"2147761686","fullName":"\\N \\N \\N","firstName":"\\N","lastName":"\\N","middleName":"\\N","gender":"\\N","birthDate":"\\N","birthPlace":"\\N","passportData":"\\N \\N \\N \\N","inn":"4201002421","address":"f","phone":"74201002421","formattedPhone":"+7 (420) 100-24-21"},"74220020218":{"id":"1928848660","fullName":"\\N \\N \\N","firstName":"\\N","lastName":"\\N","middleName":"\\N","gender":"\\N","birthDate":"\\N","birthPlace":"\\N","passportData":"\\N \\N \\N \\N","inn":"4220020218","address":"f","phone":"74220020218","formattedPhone":"+7 (422) 002-02-18"},"74217154966":{"id":"1222371767","fullName":"\\N \\N \\N","firstName":"\\N","lastName":"\\N","middleName":"\\N","gender":"\\N","birthDate":"\\N","birthPlace":"\\N","passportData":"\\N \\N \\N \\N","inn":"4217154966","address":"f","phone":"74217154966","formattedPhone":"+7 (421) 715-49-66"},"74205233268":{"id":"1222371768","fullName":"\\N \\N \\N","firstName":"\\N","lastName":"\\N","middleName":"\\N","gender":"\\N","birthDate":"\\N","birthPlace":"\\N","passportData":"\\N \\N \\N \\N","inn":"4205233268","address":"f","phone":"74205233268","formattedPhone":"+7 (420) 523-32-68"},"74202030492":{"id":"644096357","fullName":"\\N \\N \\N","firstName":"\\N","lastName":"\\N","middleName":"\\N","gender":"\\N","birthDate":"\\N","birthPlace":"\\N","passportData":"\\N \\N \\N \\N","inn":"4202030492","address":"f","phone":"74202030492","formattedPhone":"+7 (420) 203-04-92"},"74205172880":{"id":"2154726993","fullName":"\\N \\N \\N","firstName":"\\N","lastName":"\\N","middleName":"\\N","gender":"\\N","birthDate":"\\N","birthPlace":"\\N","passportData":"\\N \\N \\N \\N","inn":"4205172880","address":"f","phone":"74205172880","formattedPhone":"+7 (420) 517-28-80"},"74205114038":{"id":"1356759996","fullName":"\\N \\N \\N","firstName":"\\N","lastName":"\\N","middleName":"\\N","gender":"\\N","birthDate":"\\N","birthPlace":"\\N","passportData":"\\N \\N \\N \\N","inn":"4205114038","address":"f","phone":"74205114038","formattedPhone":"+7 (420) 511-40-38"},"74239002580":{"id":"2131139348","fullName":"\\N \\N \\N","firstName":"\\N","lastName":"\\N","middleName":"\\N","gender":"\\N","birthDate":"\\N","birthPlace":"\\N","passportData":"\\N \\N \\N \\N","inn":"4239002580","address":"f","phone":"74239002580","formattedPhone":"+7 (423) 900-25-80"},"74205090958":{"id":"1356759997","fullName":"\\N \\N \\N","firstName":"\\N","lastName":"\\N","middleName":"\\N","gender":"\\N","birthDate":"\\N","birthPlace":"\\N","passportData":"\\N \\N \\N \\N","inn":"4205090958","address":"f","phone":"74205090958","formattedPhone":"+7 (420) 509-09-58"},"74209027690":{"id":"637638042","fullName":"\\N \\N \\N","firstName":"\\N","lastName":"\\N","middleName":"\\N","gender":"\\N","birthDate":"\\N","birthPlace":"\\N","passportData":"\\N \\N \\N \\N","inn":"4209027690","address":"f","phone":"74209027690","formattedPhone":"+7 (420) 902-76-90"},"74234009863":{"id":"637636369","fullName":"\\N \\N \\N","firstName":"\\N","lastName":"\\N","middleName":"\\N","gender":"\\N","birthDate":"\\N","birthPlace":"\\N","passportData":"\\N \\N \\N \\N","inn":"4234009863","address":"f","phone":"74234009863","formattedPhone":"+7 (423) 400-98-63"},"74250000508":{"id":"637636370","fullName":"\\N \\N \\N","firstName":"\\N","lastName":"\\N","middleName":"\\N","gender":"\\N","birthDate":"\\N","birthPlace":"\\N","passportData":"\\N \\N \\N \\N","inn":"4250000508","address":"f","phone":"74250000508","formattedPhone":"+7 (425) 000-05-08"},"74216002689":{"id":"659312624","fullName":"\\N \\N \\N","firstName":"\\N","lastName":"\\N","middleName":"\\N","gender":"\\N","birthDate":"\\N","birthPlace":"\\N","passportData":"\\N \\N \\N \\N","inn":"4216002689","address":"f","phone":"74216002689","formattedPhone":"+7 (421) 600-26-89"},"74238017738":{"id":"659311902","fullName":"\\N \\N \\N","firstName":"\\N","lastName":"\\N","middleName":"\\N","gender":"\\N","birthDate":"\\N","birthPlace":"\\N","passportData":"\\N \\N \\N \\N","inn":"4238017738","address":"f","phone":"74238017738","formattedPhone":"+7 (423) 801-77-38"},"74205396456":{"id":"2131144552","fullName":"\\N \\N \\N","firstName":"\\N","lastName":"\\N","middleName":"\\N","gender":"\\N","birthDate":"\\N","birthPlace":"\\N","passportData":"\\N \\N \\N \\N","inn":"4205396456","address":"f","phone":"74205396456","formattedPhone":"+7 (420) 539-64-56"},"74253013390":{"id":"1222374545","fullName":"\\N \\N \\N","firstName":"\\N","lastName":"\\N","middleName":"\\N","gender":"\\N","birthDate":"\\N","birthPlace":"\\N","passportData":"\\N \\N \\N \\N","inn":"4253013390","address":"f","phone":"74253013390","formattedPhone":"+7 (425) 301-33-90"},"74205056280":{"id":"637636250","fullName":"\\N \\N \\N","firstName":"\\N","lastName":"\\N","middleName":"\\N","gender":"\\N","birthDate":"\\N","birthPlace":"\\N","passportData":"\\N \\N \\N \\N","inn":"4205056280","address":"f","phone":"74205056280","formattedPhone":"+7 (420) 505-62-80"},"74252000630":{"id":"644095138","fullName":"\\N \\N \\N","firstName":"\\N","lastName":"\\N","middleName":"\\N","gender":"\\N","birthDate":"\\N","birthPlace":"\\N","passportData":"\\N \\N \\N \\N","inn":"4252000630","address":"f","phone":"74252000630","formattedPhone":"+7 (425) 200-06-30"},"74228010469":{"id":"644095139","fullName":"\\N \\N \\N","firstName":"\\N","lastName":"\\N","middleName":"\\N","gender":"\\N","birthDate":"\\N","birthPlace":"\\N","passportData":"\\N \\N \\N \\N","inn":"4228010469","address":"f","phone":"74228010469","formattedPhone":"+7 (422) 801-04-69"},"74206024725":{"id":"2131152318","fullName":"\\N \\N \\N","firstName":"\\N","lastName":"\\N","middleName":"\\N","gender":"\\N","birthDate":"\\N","birthPlace":"\\N","passportData":"\\N \\N \\N \\N","inn":"4206024725","address":"f","phone":"74206024725","formattedPhone":"+7 (420) 602-47-25"},"74205194428":{"id":"2131152373","fullName":"\\N \\N \\N","firstName":"\\N","lastName":"\\N","middleName":"\\N","gender":"\\N","birthDate":"\\N","birthPlace":"\\N","passportData":"\\N \\N \\N \\N","inn":"4205194428","address":"f","phone":"74205194428","formattedPhone":"+7 (420) 519-44-28"},"74217148761":{"id":"914965872","fullName":"\\N \\N \\N","firstName":"\\N","lastName":"\\N","middleName":"\\N","gender":"\\N","birthDate":"\\N","birthPlace":"\\N","passportData":"\\N \\N \\N \\N","inn":"4217148761","address":"f","phone":"74217148761","formattedPhone":"+7 (421) 714-87-61"},"74223057390":{"id":"647671704","fullName":"\\N \\N \\N","firstName":"\\N","lastName":"\\N","middleName":"\\N","gender":"\\N","birthDate":"\\N","birthPlace":"\\N","passportData":"\\N \\N \\N \\N","inn":"4223057390","address":"f","phone":"74223057390","formattedPhone":"+7 (422) 305-73-90"},"74205332759":{"id":"2131153317","fullName":"\\N \\N \\N","firstName":"\\N","lastName":"\\N","middleName":"\\N","gender":"\\N","birthDate":"\\N","birthPlace":"\\N","passportData":"\\N \\N \\N \\N","inn":"4205332759","address":"f","phone":"74205332759","formattedPhone":"+7 (420) 533-27-59"},"74211012806":{"id":"659312644","fullName":"\\N \\N \\N","firstName":"\\N","lastName":"\\N","middleName":"\\N","gender":"\\N","birthDate":"\\N","birthPlace":"\\N","passportData":"\\N \\N \\N \\N","inn":"4211012806","address":"f","phone":"74211012806","formattedPhone":"+7 (421) 101-28-06"},"74238004496":{"id":"2147762785","fullName":"\\N \\N \\N","firstName":"\\N","lastName":"\\N","middleName":"\\N","gender":"\\N","birthDate":"\\N","birthPlace":"\\N","passportData":"\\N \\N \\N \\N","inn":"4238004496","address":"f","phone":"74238004496","formattedPhone":"+7 (423) 800-44-96"},"74205399464":{"id":"2147765086","fullName":"\\N \\N \\N","firstName":"\\N","lastName":"\\N","middleName":"\\N","gender":"\\N","birthDate":"\\N","birthPlace":"\\N","passportData":"\\N \\N \\N \\N","inn":"4205399464","address":"f","phone":"74205399464","formattedPhone":"+7 (420) 539-94-64"},"74205389730":{"id":"2216191891","fullName":"\\N \\N \\N","firstName":"\\N","lastName":"\\N","middleName":"\\N","gender":"\\N","birthDate":"\\N","birthPlace":"\\N","passportData":"\\N \\N \\N \\N","inn":"4205389730","address":"f","phone":"74205389730","formattedPhone":"+7 (420) 538-97-30"},"74234000236":{"id":"2216191897","fullName":"\\N \\N \\N","firstName":"\\N","lastName":"\\N","middleName":"\\N","gender":"\\N","birthDate":"\\N","birthPlace":"\\N","passportData":"\\N \\N \\N \\N","inn":"4234000236","address":"f","phone":"74234000236","formattedPhone":"+7 (423) 400-02-36"},"74202022325":{"id":"644094401","fullName":"\\N \\N \\N","firstName":"\\N","lastName":"\\N","middleName":"\\N","gender":"\\N","birthDate":"\\N","birthPlace":"\\N","passportData":"\\N \\N \\N \\N","inn":"4202022325","address":"f","phone":"74202022325","formattedPhone":"+7 (420) 202-23-25"},"74205379475":{"id":"2131146128","fullName":"\\N \\N \\N","firstName":"\\N","lastName":"\\N","middleName":"\\N","gender":"\\N","birthDate":"\\N","birthPlace":"\\N","passportData":"\\N \\N \\N \\N","inn":"4205379475","address":"f","phone":"74205379475","formattedPhone":"+7 (420) 537-94-75"},"74223070986":{"id":"1901314711","fullName":"\\N \\N \\N","firstName":"\\N","lastName":"\\N","middleName":"\\N","gender":"\\N","birthDate":"\\N","birthPlace":"\\N","passportData":"\\N \\N \\N \\N","inn":"4223070986","address":"f","phone":"74223070986","formattedPhone":"+7 (422) 307-09-86"},"74205072028":{"id":"637637323","fullName":"\\N \\N \\N","firstName":"\\N","lastName":"\\N","middleName":"\\N","gender":"\\N","birthDate":"\\N","birthPlace":"\\N","passportData":"\\N \\N \\N \\N","inn":"4205072028","address":"f","phone":"74205072028","formattedPhone":"+7 (420) 507-20-28"},"74205085877":{"id":"637637388","fullName":"\\N \\N \\N","firstName":"\\N","lastName":"\\N","middleName":"\\N","gender":"\\N","birthDate":"\\N","birthPlace":"\\N","passportData":"\\N \\N \\N \\N","inn":"4205085877","address":"f","phone":"74205085877","formattedPhone":"+7 (420) 508-58-77"},"74205101039":{"id":"644094687","fullName":"\\N \\N \\N","firstName":"\\N","lastName":"\\N","middleName":"\\N","gender":"\\N","birthDate":"\\N","birthPlace":"\\N","passportData":"\\N \\N \\N \\N","inn":"4205101039","address":"f","phone":"74205101039","formattedPhone":"+7 (420) 510-10-39"},"74205400448":{"id":"2147763994","fullName":"\\N \\N \\N","firstName":"\\N","lastName":"\\N","middleName":"\\N","gender":"\\N","birthDate":"\\N","birthPlace":"\\N","passportData":"\\N \\N \\N \\N","inn":"4205400448","address":"f","phone":"74205400448","formattedPhone":"+7 (420) 540-04-48"},"74222003176":{"id":"2147764008","fullName":"\\N \\N \\N","firstName":"\\N","lastName":"\\N","middleName":"\\N","gender":"\\N","birthDate":"\\N","birthPlace":"\\N","passportData":"\\N \\N \\N \\N","inn":"4222003176","address":"f","phone":"74222003176","formattedPhone":"+7 (422) 200-31-76"},"74212125577":{"id":"659312615","fullName":"\\N \\N \\N","firstName":"\\N","lastName":"\\N","middleName":"\\N","gender":"\\N","birthDate":"\\N","birthPlace":"\\N","passportData":"\\N \\N \\N \\N","inn":"4212125577","address":"f","phone":"74212125577","formattedPhone":"+7 (421) 212-55-77"}}