{"71399315580":{"Фамилия":"СМИРНОВ","_0":"СМИРНОВ","Имя":"ЮРИЙ","_1":"ЮРИЙ","Отчество":"МИХАЙЛОВИЧ","_2":"МИХАЙЛОВИЧ","Дата рождения":"12.05.1979","_3":"12.05.1979","Номер телефоа":"71399315580","_4":"71399315580","СНИЛС":"13993155800","_5":"13993155800","ИНН":"231119484877","_6":"231119484877","Почта":"","_7":"","lastName":"СМИРНОВ","firstName":"ЮРИЙ","middleName":"МИХАЙЛОВИЧ","fullName":"СМИРНОВ ЮРИЙ МИХАЙЛОВИЧ","birthDate":"12.05.1979","phone":"71399315580","formattedPhone":"+7 (139) 931-55-80","snils":"13993155800","inn":"231119484877","email":""}}